odoo/addons/ssi_risk_management/README.rst
odoo/addons/ssi_risk_management/__init__.py
odoo/addons/ssi_risk_management/__manifest__.py
odoo/addons/ssi_risk_management/menu.xml
odoo/addons/ssi_risk_management/models/__init__.py
odoo/addons/ssi_risk_management/models/res_company.py
odoo/addons/ssi_risk_management/models/res_config_settings.py
odoo/addons/ssi_risk_management/security/ir_module_category_data.xml
odoo/addons/ssi_risk_management/static/description/icon.png
odoo/addons/ssi_risk_management/static/description/risk-assessment-template.odt
odoo14_addon_ssi_risk_management-14.0.1.0.0.dist-info/METADATA
odoo14_addon_ssi_risk_management-14.0.1.0.0.dist-info/WHEEL
odoo14_addon_ssi_risk_management-14.0.1.0.0.dist-info/top_level.txt
odoo14_addon_ssi_risk_management-14.0.1.0.0.dist-info/RECORD
